CHANGELOG.md
LICENSE
MANIFEST.in
README.md
requirements.txt
setup.py
weshare/__init__.py
weshare/sdk/__init__.py
weshare/sdk/utils/__init__.py
weshare/sdk/utils/config.py
weshare/sdk/utils/daemon.py
weshare/sdk/utils/logger.py
weshare_sdk_python.egg-info/PKG-INFO
weshare_sdk_python.egg-info/SOURCES.txt
weshare_sdk_python.egg-info/dependency_links.txt
weshare_sdk_python.egg-info/namespace_packages.txt
weshare_sdk_python.egg-info/requires.txt
weshare_sdk_python.egg-info/top_level.txt