Metadata-Version: 1.1
Name: weshare-sdk-python
Version: 0.0.1
Summary: The official WeShare SDK for the Python programming language.
Home-page: https://github.com/banyq/weshare-sdk-python
Author: WeShare SDK Group
Author-email: banqing@banyq.com
License: Apache License 2.0
Platform: UNKNOWN
Classifier: Development Status :: 5 - Production/Stable
Classifier: Intended Audience :: Developers
Classifier: Natural Language :: English
Classifier: License :: OSI Approved :: Apache Software License
Classifier: Programming Language :: Python
Classifier: Programming Language :: Python :: 2.6
Classifier: Programming Language :: Python :: 2.7
Classifier: Programming Language :: Python :: 3
Classifier: Programming Language :: Python :: 3.3
Classifier: Programming Language :: Python :: 3.4
Classifier: Programming Language :: Python :: 3.5
